easypostgre/__init__.py
easypostgre/customdecorators.py
easypostgre/db.py
easypostgre/decorators.py
easypostgre-0.0.5.dist-info/LICENSE
easypostgre-0.0.5.dist-info/METADATA
easypostgre-0.0.5.dist-info/WHEEL
easypostgre-0.0.5.dist-info/top_level.txt
easypostgre-0.0.5.dist-info/RECORD
